basic_utilities/__init__.py
basic_utilities/settings.py
images/__init__.py
postfiatsecurity/__init__.py
postfiatsecurity/hash_tools.py
task_manager/__init__.py
task_manager/basic_tasks.py
user_login/__init__.py
user_login/credential_input.py
wallet_ux/__init__.py
wallet_ux/pft_wallet.py
wallet_ux/prod_wallet.py
wallet_ux/verify_domain.py
pftpythonclient-0.1.0.dist-info/LICENSE
pftpythonclient-0.1.0.dist-info/METADATA
pftpythonclient-0.1.0.dist-info/WHEEL
pftpythonclient-0.1.0.dist-info/top_level.txt
pftpythonclient-0.1.0.dist-info/RECORD
