Metadata-Version: 2.1
Name: pftpythonclient
Version: 0.1.0
Summary: Basic Post Fiat Python Functionality
Home-page: https://github.com/postfiatorg/pftpyclient
Author: PFAdmin
Author-email: admin@postfiat.com
Classifier: Programming Language :: Python :: 3
Classifier: License :: OSI Approved :: MIT License
Classifier: Operating System :: OS Independent
Requires-Python: >=3.11
License-File: LICENSE
Requires-Dist: numpy
Requires-Dist: pandas
Requires-Dist: sqlalchemy
Requires-Dist: cryptography
Requires-Dist: xrpl-py
Requires-Dist: wxPython
Requires-Dist: requests
Requires-Dist: toml
